openscad_py/__init__.py
openscad_py/combinations.py
openscad_py/complex.py
openscad_py/entity.py
openscad_py/entity_selector.py
openscad_py/objects_2d.py
openscad_py/objects_3d.py
openscad_py/others.py
openscad_py/pirimitive.py
openscad_py/transformations.py
openscad_py/typing.py
openscad_py-0.0.1.dist-info/LICENSE.md
openscad_py-0.0.1.dist-info/METADATA
openscad_py-0.0.1.dist-info/WHEEL
openscad_py-0.0.1.dist-info/top_level.txt
openscad_py-0.0.1.dist-info/RECORD
